{"company": {"org_id": "T000056654", "org_name_cn": "中际旭创股份有限公司", "org_short_name_cn": "中际旭创", "org_name_en": "Zhongji Innolight Co.,Ltd.", "org_short_name_en": "ZHONGJI INNOLIGHT", "main_operation_business": "高端光通信收发模块以及光器件的研发、生产及销售。", "operating_scope": "　　一般项目：通信设备制造；光通信设备制造；光通信设备销售；电子元器件制造；电子元器件零售；光电子器件制造；光电子器件销售；集成电路芯片及产品制造；技术服务、技术开发、技术咨询、技术交流、技术转让、技术推广；货物进出口；以自有资金从事投资活动；企业管理；非居住房地产租赁。（除依法须经批准的项目外，凭营业执照依法自主开展经营活动）", "district_encode": "370681", "org_cn_introduction": "中际旭创股份有限公司的主营业务是高端光通信收发模块以及光器件的研发、生产及销售。公司的主要产品是光通信收发模块、光组件、汽车光电子。", "legal_representative": "刘圣", "general_manager": "刘圣", "secretary": "王军", "established_date": 1119801600000, "reg_asset": 1111118334.0, "staff_num": 8542, "telephone": "86-535-8573360", "postcode": "265700", "fax": "86-535-8573360", "email": "info@zj-innolight.com;zhongji300308@zj-innolight.com", "org_website": "www.zj-innolight.com", "reg_address_cn": "山东省烟台市龙口市诸由观镇驻地", "reg_address_en": null, "office_address_cn": "山东省烟台市龙口市诸由观镇驻地", "office_address_en": null, "currency_encode": "019001", "currency": "CNY", "listed_date": 1333987200000, "provincial_name": "山东省", "actual_controller": "王伟修 (12.25%)", "classi_name": "民营企业", "pre_name_cn": "山东中际电工装备股份有限公司", "chairman": "刘圣", "executives_nums": 11, "actual_issue_vol": 16670000.0, "issue_price": 20.0, "actual_rc_net_amt": 297661600.0, "pe_after_issuing": 26.73, "online_success_rate_of_issue": 0.37573119, "affiliate_industry": {"ind_code": "BK0029", "ind_name": "通信设备"}}}