{"company": {"org_id": "T000058563", "org_name_cn": "苏州斯莱克精密设备股份有限公司", "org_short_name_cn": "斯莱克", "org_name_en": "Suzhou Slac Precision Equipment Co.,Ltd.", "org_short_name_en": "SLAC", "main_operation_business": "高速易拉盖、易拉罐等金属包装制品生产设备的研发、设计、生产、装配调试，相关精密模具、智能检测设备、零备件的研发、加工制造等业务。", "operating_scope": "　　研发、生产、加工精冲模、冲压系统和农产品、食品包装的新技术、新设备及相关零配件，并提供相关服务；各种生产易拉盖、易拉罐、金属包装的设备，相关辅助设备和精冲模的再制造；销售公司自产产品。（依法须经批准的项目，经相关部门批准后方可开展经营活动）许可项目：包装装潢印刷品印刷（依法须经批准的项目，经相关部门批准后方可开展经营活动，具体经营项目以审批结果为准）。一般项目：电池零配件生产；电池零配件销售；汽车零部件研发；汽车零部件及配件制造（除依法须经批准的项目外，凭营业执照依法自主开展经营活动）", "district_encode": "320506", "org_cn_introduction": "苏州斯莱克精密设备股份有限公司的主营业务是高速易拉盖、易拉罐等金属包装制品生产设备的研发、设计、生产、装配调试，相关精密模具、智能检测设备、零备件的研发、加工制造等业务。公司的主要产品是易拉盖/罐高速生产设备和系统改造、新能源汽车电池壳、智能检测设备、数码印罐迷你线、光伏发电。公司提供的数码印罐迷你线生产速度最高200罐/分钟，实现最快当天交付，产品性能处于国际领先地位，并获得行业权威会议“CantechGrandTour2019”颁发的国际供应商创新金奖，技术水平获得了全球易拉罐制罐行业的认可。", "legal_representative": "安旭", "general_manager": "安旭", "secretary": "吴晓燕", "established_date": 1073318400000, "reg_asset": 648399994.0, "staff_num": 2076, "telephone": "86-512-66590361", "postcode": "215164", "fax": "86-512-66248543", "email": "stock@slac.com.cn", "org_website": "www.slac.com.cn", "reg_address_cn": "江苏省苏州市吴中区胥口镇孙武路1028号", "reg_address_en": null, "office_address_cn": "江苏省苏州市吴中区胥口镇孙武路1028号", "office_address_en": null, "currency_encode": "019001", "currency": "CNY", "listed_date": 1390924800000, "provincial_name": "江苏省", "actual_controller": "安旭 (34.14%)", "classi_name": "外资企业", "pre_name_cn": null, "chairman": "安旭", "executives_nums": 18, "actual_issue_vol": 13309247.0, "issue_price": 35.15, "actual_rc_net_amt": 231107818.0, "pe_after_issuing": 22.29, "online_success_rate_of_issue": 1.64658651, "affiliate_industry": {"ind_code": "BK0018", "ind_name": "专用设备"}}}