{"company": {"org_id": "Q00018875A", "org_name_cn": "苏州锴威特半导体股份有限公司", "org_short_name_cn": "锴威特", "org_name_en": "Suzhou Convert Semiconductor Co.,Ltd.", "org_short_name_en": "CONVERTSEMI", "main_operation_business": "功率半导体的设计、研发和销售，并提供相关技术服务。", "operating_scope": "　　半导体分立器件、集成电路和系统模块的生产、设计、测试、销售；自营和代理各类商品及技术的进出口业务；软件设计、开发、销售。（依法须经批准的项目，经相关部门批准后方可开展经营活动）", "district_encode": "320582", "org_cn_introduction": "苏州锴威特半导体股份有限公司的主营业务是功率半导体的设计、研发和销售，并提供相关技术服务。公司的主要产品是功率器件及功率IC两大类，同时也为部分客户提供芯片设计及工艺开发等技术服务。", "legal_representative": "罗寅", "general_manager": "罗寅", "secretary": "严泓", "established_date": 1421856000000, "reg_asset": 73684211.0, "staff_num": 190, "telephone": "86-512-58979950", "postcode": "215600", "fax": null, "email": "zhengq@convertsemi.com", "org_website": "www.convertsemi.com", "reg_address_cn": "江苏省苏州市张家港市杨舍镇华昌路10号沙洲湖科创园B2幢01室", "reg_address_en": null, "office_address_cn": "江苏省苏州市张家港市杨舍镇华昌路10号沙洲湖科创园B2幢01室", "office_address_en": null, "currency_encode": "019001", "currency": "CNY", "listed_date": 1692288000000, "provincial_name": "江苏省", "actual_controller": "丁国华 (16.43%)", "classi_name": "民营企业", "pre_name_cn": null, "chairman": "丁国华", "executives_nums": 12, "actual_issue_vol": 18421053.0, "issue_price": 40.83, "actual_rc_net_amt": 664798900.0, "pe_after_issuing": 60.69, "online_success_rate_of_issue": 0.04231394, "affiliate_industry": {"ind_code": "BK0021", "ind_name": "半导体"}}}