{"company": {"org_id": "T000242179", "org_name_cn": "正元智慧集团股份有限公司", "org_short_name_cn": "正元智慧", "org_name_en": "Zhengyuan Zhihui Group Co.,Ltd.", "org_short_name_en": "ZHENGYUAN ZHIHUI", "main_operation_business": "智慧校园、智慧园区和行业智慧化系统建设及增值运营服务。", "operating_scope": "　　许可项目：第一类增值电信业务；第二类增值电信业务；建筑智能化系统设计；建设工程施工；职业中介活动；电热食品加工设备生产（依法须经批准的项目，经相关部门批准后方可开展经营活动，具体经营项目以审批结果为准）。一般项目：技术服务、技术开发、技术咨询、技术交流、技术转让、技术推广；软件开发；软件销售；人工智能应用软件开发；人工智能行业应用系统集成服务；人工智能硬件销售；物联网技术研发；物联网技术服务；物联网应用服务；大数据服务；数据处理服务；互联网数据服务；信息系统集成服务；信息系统运行维护服务；安全技术防范系统设计施工服务；节能管理服务；洗烫服务；洗染服务；软件外包服务；人力资源服务（不含职业中介活动、劳务派遣服务）；计算机软硬件及外围设备制造；计算机软硬件及辅助设备零售；计算机软硬件及辅助设备批发；计算机及办公设备维修；移动终端设备制造；移动终端设备销售；智能仪器仪表制造；智能仪器仪表销售；终端计量设备制造；终端计量设备销售；智能家庭消费设备销售；电热食品加工设备销售；制冷、空调设备制造；制冷、空调设备销售；厨具卫具及日用杂品零售；风机、风扇制造；风机、风扇销售；燃气器具生产；环境保护专用设备销售；环境保护专用设备制造；金属制日用品制造；家用电器销售；电子产品销售；办公设备销售；洗涤机械销售；建筑材料销售；货物进出口（除依法须经批准的项目外，凭营业执照依法自主开展经营活动）", "district_encode": "330110", "org_cn_introduction": "正元智慧集团股份有限公司的主营业务是智慧校园、智慧园区和行业智慧化系统建设及增值运营服务。公司的主要产品是高校智慧校园、基础教育数字化、智慧政企、云服务、投资运营服务、智能制造。", "legal_representative": "陈艺戎", "general_manager": "陈根清", "secretary": "周军辉", "established_date": 952876800000, "reg_asset": 142102465.0, "staff_num": 2104, "telephone": "86-571-88994988", "postcode": "311121", "fax": "86-571-88994793", "email": "ir@hzsun.com", "org_website": "www.hzsun.com", "reg_address_cn": "浙江省杭州市余杭区舒心路359号正元智慧大厦A幢17层", "reg_address_en": null, "office_address_cn": "浙江省杭州市余杭区舒心路359号正元智慧大厦A幢", "office_address_en": null, "currency_encode": "019001", "currency": "CNY", "listed_date": 1492704000000, "provincial_name": "浙江省", "actual_controller": "陈坚 (22.59%)", "classi_name": "民营企业", "pre_name_cn": "浙江正元智慧科技股份有限公司", "chairman": "陈艺戎", "executives_nums": 17, "actual_issue_vol": 16666667.0, "issue_price": 12.35, "actual_rc_net_amt": 158220000.0, "pe_after_issuing": 22.98, "online_success_rate_of_issue": 0.0129471, "affiliate_industry": {"ind_code": "BK0030", "ind_name": "计算机设备"}}}