{"company": {"org_id": "T000291309", "org_name_cn": "广东惠威电声科技股份有限公司", "org_short_name_cn": "惠威科技", "org_name_en": "Hivi Acoustics Technology Co.,Ltd.", "org_short_name_en": "HiVi Tech", "main_operation_business": "各类音响设备、扬声器的研发、生产和销售。", "operating_scope": "　　一般项目：技术服务、技术开发、技术咨询、技术交流、技术转让、技术推广；电子专用材料研发；广播电视设备制造（不含广播电视传输设备）；影视录放设备制造；音响设备制造；音响设备销售；家用视听设备销售；家用电器销售。（除依法须经批准的项目外，凭营业执照依法自主开展经营活动）（以上项目不涉及外商投资准入特别管理措施）", "district_encode": "442000", "org_cn_introduction": "广东惠威电声科技股份有限公司的主营业务是各类音响设备、扬声器的研发、生产和销售。公司的主要产品是多媒体音响系列、家庭影院音响系列、专业音响系列、汽车音响系列、公共广播系列、喇叭系列及耳机系列。公司产品被评为广东省名牌产品，多次获得美国国际消费电子展（CES, Consumer Electronics Show）荣誉，各细分产品也获得了较高的市场评价。", "legal_representative": "HONGBO YAO", "general_manager": "JUNJIE MICHAEL YAO", "secretary": "况飞帆", "established_date": 867081600000, "reg_asset": 147643412.0, "staff_num": 613, "telephone": "86-755-26904655;86-20-34919808", "postcode": "519090", "fax": "86-755-26904655;86-20-84901370", "email": "zqb@hivi.com", "org_website": "www.hivi.com", "reg_address_cn": "广东省中山市南朗街道翠亨新区扬帆路8号万滨万潮广场7栋101卡", "reg_address_en": null, "office_address_cn": "广东省珠海市金湾区联港工业区大林山片区东成路南1号珠海惠威科技有限公司", "office_address_en": null, "currency_encode": "019001", "currency": "CNY", "listed_date": 1500566400000, "provincial_name": "广东省", "actual_controller": "HONGBO YAO (61.26%)，HUIFANG CHEN (3.54%)", "classi_name": "外资企业", "pre_name_cn": "广州惠威电声科技股份有限公司", "chairman": "HONGBO YAO", "executives_nums": 13, "actual_issue_vol": 20780000.0, "issue_price": 8.97, "actual_rc_net_amt": 154066300.0, "pe_after_issuing": 22.97, "online_success_rate_of_issue": 0.0222163, "affiliate_industry": {"ind_code": "BK0024", "ind_name": "消费电子"}}}