{"company": {"org_id": "T000028400", "org_name_cn": "亚光科技集团股份有限公司", "org_short_name_cn": "亚光科技", "org_name_en": "Yaguang Technology Group Company Limited", "org_short_name_en": "YaGuang Technology", "main_operation_business": "高性能微波电子、航海装备及其产品的研发设计与制造。", "operating_scope": "　　许可项目：船舶制造;船舶改装;船舶拆除;船舶设计;船舶修理;航天设备制造;民用航空器零部件设计和生产;建筑智能化系统设计;建设工程设计;特种设备制造;特种设备设计;特种设备安装改造修理。(依法须经批准的项目,经相关部门批准后方可开展经营活动,具体经营项目以相关部门批准文件或许可证件为准)一般项目：船舶销售;船用配套设备制造;合成材料销售;高性能纤维及复合材料销售;新材料技术研发;国内船舶代理;货物进出口;技术进出口;进出口代理;工业设计服务;专业设计服务;工程技术服务(规划管理、勘察、设计、监理除外);技术服务、技术开发、技术咨询、技术交流、技术转让、技术推广;日用百货销售;日用品销售;日用品批发;五金产品零售;五金产品批发;电子产品销售;电子元器件制造;电子元器件零售;电子元器件批发;电子专用材料制造;电子专用设备制造;电子专用设备销售;其他电子器件制造;集成电路芯片及产品制造;集成电路芯片及产品销售;集成电路芯片设计及服务;集成电路销售;集成电路设计;通信设备制造;通用零部件制造;机械电气设备制造;机械电气设备销售;机械零件、零部件加工;机械零件、零部件销售;专用设备制造(不含许可类专业设备制造);通用设备制造(不含特种设备制造);半导体器件专用设备制造;半导体器件专用设备销售;半导体分立器件制造;半导体分立器件销售;通讯设备销售;智能车载设备制造;智能基础制造装备制造;智能基础制造装备销售;智能无人飞行器制造;智能无人飞行器销售;智能车载设备销售;智能控制系统集成;人工智能硬件销售;人工智能行业应用系统集成服务;雷达及配套设备制造;光通信设备制造;通用设备修理;专用设备修理;信息安全设备制造;信息系统集成服务;信息系统运行维护服务;安全技术防范系统设计施工服务;非居住房地产租赁;土地使用权租赁;船舶租赁;游艇租赁;机械设备租赁;租赁服务(不含许可类租赁服务)。(除依法须经批准的项目外,凭营业执照依法自主开展经营活动)", "district_encode": "430981", "org_cn_introduction": "亚光科技集团股份有限公司的主营业务是高性能微波电子、航海装备及其产品的研发设计与制造。公司的主要产品是公务船艇、游艇游船、防务装备、微波电路与组件、半导体器件、安防及专网通信、电磁环境构建。公司是国内领先的船艇设计、生产、销售及服务企业，也是国内首家游艇制造上市企业。旗下自主品牌“太阳鸟”在行业内具有较高知名度，多次荣获亚洲最佳船艇品牌、中国最佳船艇品牌金帆奖、中国工业设计十佳创新型企业等权威奖项，产品设计能力与品牌影响力得到市场广泛认可。", "legal_representative": "李跃先", "general_manager": "胡代荣", "secretary": "饶冰笑", "established_date": 1054569600000, "reg_asset": 1021834123.0, "staff_num": 1419, "telephone": "86-731-84445689", "postcode": "413100", "fax": "86-731-88816828", "email": "stock@cnsunbird.com", "org_website": "www.ygkjgroup.com", "reg_address_cn": "湖南省益阳市沅江市游艇工业园", "reg_address_en": null, "office_address_cn": "湖南省益阳市沅江市游艇工业园", "office_address_en": null, "currency_encode": "019001", "currency": "CNY", "listed_date": 1285603200000, "provincial_name": "湖南省", "actual_controller": "李跃先 (16.07%)", "classi_name": "民营企业", "pre_name_cn": "太阳鸟游艇股份有限公司", "chairman": "李跃先", "executives_nums": 12, "actual_issue_vol": 22000000.0, "issue_price": 28.88, "actual_rc_net_amt": 586868335.0, "pe_after_issuing": 96.27, "online_success_rate_of_issue": 0.52220266, "affiliate_industry": {"ind_code": "BK0091", "ind_name": "军工电子"}}}