{"company": {"org_id": "T000158880", "org_name_cn": "广东联泰环保股份有限公司", "org_short_name_cn": "联泰环保", "org_name_en": "Guangdong Liantai Environmental Protection Co.,Ltd.", "org_short_name_en": "Liantai Environmental Protection(LTEP)", "main_operation_business": "城乡污水处理设施的投资、建设和运营管理，提供污水收集、输送和/或终端污水处理服务。", "operating_scope": "　　水环境污染防治服务；污水处理及其再生利用；生态恢复及生态保护服务；固体废物治理；市政设施管理；环保咨询服务；环境应急治理服务；环境保护专用设备制造；环境保护专用设备销售；污泥处理装备制造；再生资源加工；再生资源回收（除生产性废旧金属）；再生资源销售；新兴能源技术研发；生物质能技术服务；太阳能发电技术服务；以自有资金从事投资活动。（依法须经批准的项目，经相关部门批准后方可开展经营活动）", "district_encode": "440507", "org_cn_introduction": "广东联泰环保股份有限公司的主营业务是城乡污水处理设施的投资、建设和运营管理，提供污水收集、输送和/或终端污水处理服务。公司的主要产品是污水处理、污泥处理。公司是国内污水处理领域的优秀民营企业之一，是专注于污水处理行业的区域性重要企业。公司以城市重大项目的投资建设为切入点，通过打造精品工程，积累了丰富的行业投资、建设及运营经验，形成较强的技术实力并建立了高效的管理运营体系，不断形成核心竞争优势。经过数年发展，公司项目运营规模不断增大，在湖南和广东区域拥有多个投资运营项目。截至2024年12月31日，公司已建成投入运营的污水处理项目总处理规模（包括分散式污水处理站点）已达137万吨/日。", "legal_representative": "黄建勲", "general_manager": "张荣", "secretary": "李启亮", "established_date": 1144944000000, "reg_asset": 584490586.0, "staff_num": 723, "telephone": "86-754-89650738", "postcode": "515041", "fax": "86-754-89650738", "email": "ltep@lt-hbgf.com", "org_website": "www.lt-hbgf.com", "reg_address_cn": "广东省汕头市龙湖区中山东路黄厝围龙珠水质净化厂", "reg_address_en": null, "office_address_cn": "广东省汕头市龙湖区中山东路黄厝围龙珠水质净化厂", "office_address_en": null, "currency_encode": "019001", "currency": "CNY", "listed_date": 1492012800000, "provincial_name": "广东省", "actual_controller": "黄建勲 (26.55%)，黄婉茹 (16.51%)，黄振达 (13.10%)", "classi_name": "民营企业", "pre_name_cn": null, "chairman": "黄建勲", "executives_nums": 14, "actual_issue_vol": 53340000.0, "issue_price": 5.96, "actual_rc_net_amt": 277297200.0, "pe_after_issuing": 22.98, "online_success_rate_of_issue": 0.03464106, "affiliate_industry": {"ind_code": "BK0081", "ind_name": "环境治理"}}}