{"company": {"org_id": "T000226019", "org_name_cn": "中持水务股份有限公司", "org_short_name_cn": "中持股份", "org_name_en": "Csd Water Service Co.,Ltd.", "org_short_name_en": "CSD Water Service", "main_operation_business": "城镇污水处理、工业园区及工业污水处理、综合环境治理。", "operating_scope": "　　研究、开发污水处理及污泥处置相关技术；环保设施运营管理；环保工程承包；提供环保技术咨询、技术服务、技术开发、技术支持；销售自行研发产品、环保设备、仪器成套、建筑材料、五金交电、机械设备；货物进出口、技术进出口、代理进出口；建设工程项目管理；水污染治理；城市公用设施的综合管理；城市园林绿化；市政建设及规划咨询；建筑工程机械与设备租赁；工程勘察；工程设计。（市场主体依法自主选择经营项目，开展经营活动；工程勘察、工程设计以及依法须经批准的项目，经相关部门批准后依批准的内容开展经营活动；不得从事国家和本市产业政策禁止和限制类项目的经营活动。）", "district_encode": "110108", "org_cn_introduction": "中持水务股份有限公司的主营业务是城镇污水处理、工业园区及工业污水处理、综合环境治理。公司的主要产品是环保基础设施建造服务、运营服务、技术产品销售与技术服务。2024年3月，第二十二届水业战略论坛在北京开幕，公司荣获2023年度水业十大影响力企业。", "legal_representative": "张翼飞", "general_manager": "高志永", "secretary": "高远", "established_date": 1262188800000, "reg_asset": 255319480.0, "staff_num": 1456, "telephone": "86-10-82800655", "postcode": "100192", "fax": "86-10-82800399", "email": "investor@zchb-water.net", "org_website": "www.zchb-water.net", "reg_address_cn": "北京市海淀区西小口路66号中关村东升科技园·北领地B-2楼4层C402", "reg_address_en": null, "office_address_cn": "北京市海淀区西小口路66号中关村东升科技园·北领地B-2楼4层C402", "office_address_en": null, "currency_encode": "019001", "currency": "CNY", "listed_date": 1489420800000, "provincial_name": "北京市", "actual_controller": "许国栋 (15.95%)", "classi_name": "民营企业", "pre_name_cn": null, "chairman": "张翼飞", "executives_nums": 15, "actual_issue_vol": 25609500.0, "issue_price": 9.88, "actual_rc_net_amt": 223020200.0, "pe_after_issuing": 22.98, "online_success_rate_of_issue": 0.02627643, "affiliate_industry": {"ind_code": "BK0081", "ind_name": "环境治理"}}}