{"company": {"org_id": "Q00451D3FE", "org_name_cn": "江苏常友环保科技股份有限公司", "org_short_name_cn": "常友科技", "org_name_en": "Jiangsu Changyou Environmental Protection Technology Co., Ltd.", "org_short_name_en": "Changyou Technology", "main_operation_business": "高分子复合材料制品、轻量化夹芯材料制品的研发、生产与销售业务。", "operating_scope": "　　环保设备生产制造、研发及技术服务；能源设备配件、风力发电用玻璃钢机舱罩、玻璃钢制品、轨道交通内外饰部件、新能源汽车复合材料部件、碳纤维制品的制造及维修；复合材料、金属材料、玻璃纤维布、模具、木制品的销售；自营和代理各类商品及技术的进出口业务（国家限定企业经营或禁止进出口的商品和技术除外）。（依法须经批准的项目，经相关部门批准后方可开展经营活动）许可项目：火箭发射设备研发和制造；火箭发动机研发与制造（依法须经批准的项目，经相关部门批准后方可开展经营活动，具体经营项目以审批结果为准）一般项目：普通货物仓储服务（不含危险化学品等需许可审批的项目）；智能无人飞行器制造；智能无人飞行器销售；玻璃纤维及制品制造；玻璃纤维及制品销售；雷达及配套设备制造（除依法须经批准的项目外，凭营业执照依法自主开展经营活动）", "district_encode": "320413", "org_cn_introduction": "江苏常友环保科技股份有限公司的主营业务是高分子复合材料制品、轻量化夹芯材料制品的研发、生产与销售业务。公司的主要产品是风电机组罩体（包括机舱罩和导流罩）、风电轻量化夹芯材料（包括巴沙木制品、PVC泡沫制品、PET泡沫制品）、轨道交通车辆部件。公司先后被认定为国家高新技术企业、江苏省民营科技企业、常州市工程技术研究中心、省级专精特新中小企业、国家级专精特新“小巨人”企业。", "legal_representative": "刘文叶", "general_manager": "刘文叶", "secretary": "唐娜", "established_date": 1166457600000, "reg_asset": 44307870.99999999, "staff_num": 1228, "telephone": "86-519-68227767", "postcode": "213200", "fax": "86-519-68227767", "email": "jscy-public@jscy.vip", "org_website": "www.jscy.vip", "reg_address_cn": "江苏省常州市金坛区金坛大道92号", "reg_address_en": null, "office_address_cn": "江苏省常州市金坛区金坛经济开发区亿晶路222号", "office_address_en": null, "currency_encode": "019001", "currency": "CNY", "listed_date": 1741017600000, "provincial_name": "江苏省", "actual_controller": "刘文叶 (47.82%)，刘波涛 (5.08%)，刘文君 (0.97%)，包涵寓 (0.11%)", "classi_name": "民营企业", "pre_name_cn": null, "chairman": "刘文叶", "executives_nums": 11, "actual_issue_vol": 11080000.0, "issue_price": 28.88, "actual_rc_net_amt": 262666200.0, "pe_after_issuing": 15.7, "online_success_rate_of_issue": 0.01213058, "affiliate_industry": {"ind_code": "BK0095", "ind_name": "风电设备"}}}