{"company": {"org_id": "02600292", "org_name_cn": "国家电投集团远达环保股份有限公司", "org_short_name_cn": "远达环保", "org_name_en": "Spic Yuanda Environmental—Protection Co.,Ltd.", "org_short_name_en": "SPICYD", "main_operation_business": "脱硫脱硝除尘工程总承包、脱硫脱硝特许经营、脱硝催化剂制造及再生、水务工程及运营等业务。", "operating_scope": "　　许可项目：发电业务、输电业务、供（配）电业务。（依法须经批准的项目，经相关部门批准后方可开展经营活动，具体经营项目以相关部门批准文件或许可证件为准）一般项目：技术服务、技术开发、技术咨询、技术交流、技术转让、技术推广；大气污染治理；水环境污染防治服务；固体废物治理；环境保护专用设备制造；环境保护专用设备销售；生态环境材料制造；生活垃圾处理装备制造；生活垃圾处理装备销售；环境保护监测；环保咨询服务；节能管理服务；太阳能发电技术服务；风力发电技术服务；储能技术服务；电池制造；电池零配件销售；电池销售；新能源汽车换电设施销售；充电桩销售；资源再生利用技术研发；新能源汽车废旧动力蓄电池回收及梯次利用（不含危险废物经营）；碳减排、碳转化、碳捕捉、碳封存技术研发；温室气体排放控制装备制造；基础化学原料制造（不含危险化学品等许可类化学品的制造）；认证咨询。（除依法须经批准的项目外，凭营业执照依法自主开展经营活动）", "district_encode": "500112", "org_cn_introduction": "国家电投集团远达环保股份有限公司的主营业务是脱硫脱硝除尘工程总承包、脱硫脱硝特许经营、脱硝催化剂制造及再生、水务工程及运营等业务。公司的主要产品是脱硝催化剂。2023年度ESG报告获得万得资讯A级评价;公司获评中国上市公司协会“2024年上市公司董事会优秀实践案例”，重庆市“2024十大重庆社会责任影响力年度企业”，2024年国新杯“金牛奖ESG碳中和二十强”等荣誉。", "legal_representative": "陈斌", "general_manager": null, "secretary": "凌娟", "established_date": 772905600000, "reg_asset": 780816890.0, "staff_num": 2003, "telephone": "86-23-65933055", "postcode": "401122", "fax": "86-23-65933000", "email": "ydhb_dm@spic.com.cn;lingjuan@spic.com.cn;denglichun@spic.com.cn", "org_website": "www.zdydep.com", "reg_address_cn": "重庆市渝北区两江新区黄环北路10号1栋", "reg_address_en": null, "office_address_cn": "重庆市渝北区两江新区黄环北路10号1栋", "office_address_en": null, "currency_encode": "019001", "currency": "CNY", "listed_date": 973008000000, "provincial_name": "重庆市", "actual_controller": "国务院国有资产监督管理委员会 (43.74%)", "classi_name": "央企国资控股", "pre_name_cn": "中电投远达环保(集团)股份有限公司", "chairman": "陈斌", "executives_nums": 20, "actual_issue_vol": 60000000.0, "issue_price": 9.0, "actual_rc_net_amt": 521647485.0, "pe_after_issuing": 22.14, "online_success_rate_of_issue": 0.4443, "affiliate_industry": {"ind_code": "BK0081", "ind_name": "环境治理"}}}