{"company": {"org_id": "T001260534", "org_name_cn": "江西国科军工集团股份有限公司", "org_short_name_cn": "国科军工", "org_name_en": "Jiangxi Guoke Defence Group Co.,Ltd.", "org_short_name_en": "GUOKE DEFENCE", "main_operation_business": "导弹（火箭）固体发动机动力与控制产品及弹药装备的研发、生产与销售。", "operating_scope": "　　机械，电子产品的技术开发、加工；投资；咨询；服务；物业管理；房屋租赁；金属材料销售。（依法须经批准的项目，经相关部门批准后方可开展经营活动）", "district_encode": "360111", "org_cn_introduction": "江西国科军工集团股份有限公司的主营业务是导弹（火箭）固体发动机动力与控制产品及弹药装备的研发、生产与销售。公司的主要产品是导弹（火箭）固体发动机动力与控制产品、弹药装备。公司荣获国家科学技术进步奖、国家科学技术进步奖，是国家级专精特新“小巨人”企业。", "legal_representative": "余永安", "general_manager": "余永安", "secretary": "邓卫勇", "established_date": 1198857600000, "reg_asset": 208842028.0, "staff_num": 1002, "telephone": "86-791-88115098", "postcode": "330000", "fax": "86-791-88107858", "email": "zqb@guokegroup.com", "org_website": "www.guokegroup.com", "reg_address_cn": "江西省南昌市青山湖区南昌经济技术开发区建业大街999号", "reg_address_en": null, "office_address_cn": "江西省南昌市青山湖区南昌经济技术开发区建业大街999号", "office_address_en": null, "currency_encode": "019001", "currency": "CNY", "listed_date": 1687276800000, "provincial_name": "江西省", "actual_controller": "江西省国有资产监督管理委员会 (30.43%)", "classi_name": "省属国资控股", "pre_name_cn": "江西国科军工集团有限公司", "chairman": "余永安", "executives_nums": 10, "actual_issue_vol": 36670000.0, "issue_price": 43.67, "actual_rc_net_amt": 1442913400.0, "pe_after_issuing": 63.25, "online_success_rate_of_issue": 0.04308235, "affiliate_industry": {"ind_code": "BK0066", "ind_name": "军工装备"}}}