{"company": {"org_id": "T000251649", "org_name_cn": "福建海通发展股份有限公司", "org_short_name_cn": "海通发展", "org_name_en": "Fujian Highton Development Co.,Ltd.", "org_short_name_en": "Highton Development", "main_operation_business": "国内沿海以及国际远洋的干散货运输业务。", "operating_scope": "　　国内沿海、长江中下游及珠江三角洲普通货船运输；国内水路货物运输代理业务和国内水路船舶代理业务；船舶维修；船舶经纪；集装箱出租；港湾建设，船舶管理业务；国际船舶普通货物运输（以上均不含危化品）。（依法须经批准的项目，经相关部门批准后方可开展经营活动）", "district_encode": "350128", "org_cn_introduction": "福建海通发展股份有限公司的主营业务是国内沿海以及国际远洋的干散货运输业务。公司的主要产品是境内航区运输业务、境外航区运输业务。", "legal_representative": "曾而斌", "general_manager": "郑玉芳", "secretary": "黄甜甜", "established_date": 1237392000000, "reg_asset": 925663527.9999999, "staff_num": 355, "telephone": "86-591-88086357", "postcode": "350004", "fax": "86-591-86291786", "email": "ir@fz-highton.com", "org_website": "www.fj-highton.com", "reg_address_cn": "福建省福州市平潭县综合实验区金井湾商务营运中心3号楼17层1705-2室", "reg_address_en": null, "office_address_cn": "福建省福州市台江区长汀街23号升龙环球大厦42层", "office_address_en": null, "currency_encode": "019001", "currency": "CNY", "listed_date": 1680019200000, "provincial_name": "福建省", "actual_controller": "曾而斌 (64.23%)", "classi_name": "民营企业", "pre_name_cn": "福州海通发展股份有限公司", "chairman": "曾而斌", "executives_nums": 8, "actual_issue_vol": 41276015.0, "issue_price": 37.25, "actual_rc_net_amt": 1427932000.0, "pe_after_issuing": 22.99, "online_success_rate_of_issue": 0.04517701, "affiliate_industry": {"ind_code": "BK0048", "ind_name": "港口航运"}}}