{"company": {"org_id": "T000058929", "org_name_cn": "四川中光防雷科技股份有限公司", "org_short_name_cn": "中光防雷", "org_name_en": "Sichuan Zhongguang Lightning Protection Technologies Co.,Ltd.", "org_short_name_en": "ZG Lightning Protect", "main_operation_business": "防雷产品的研发、设计、生产和销售，防雷工程的设计和安装，提供防雷产品和防雷工程一体化的整体解决方案。", "operating_scope": "　　研发、设计、生产、销售避雷器材及设备、通讯器材（不含无线广播电视发射及地面卫星接收设备）、广电器材（不含卫星地面接收器材）、信息保护器材和设施、金属结构件、模具、电力电子元器件、电容器及配套设备、变压器、整流器和电感器、配电开关控制设备、电子工业专业设备、电子测量仪器、电工仪器仪表、实验分析仪器、塑料零件及其他塑料制品、耐火材料（不含危险化学品）；软件开发；计算机系统安全工程设计及施工；建筑物电子信息系统安全保护器材及设施、安全保护工程设计及施工；货物及技术进出口；质检技术服务（国家有专项规定的除外）；电力工程、工程咨询；销售石油焦。（工程类经营项目经营凭资质许可证经营）（依法须批准的项目，经相关部门批准后方可开展经营活动）。", "district_encode": "510117", "org_cn_introduction": "四川中光防雷科技股份有限公司的主营业务是防雷产品的研发、设计、生产和销售，防雷工程的设计和安装，提供防雷产品和防雷工程一体化的整体解决方案。公司的主要产品是通用标准品、通信防雷产品、铁路与轨道交通防雷产品、新能源防雷产品、航天国防防雷产品、非防雷产品。公司获得国家级专精特新小巨人企业（国家级）、四川省重点行业小巨人企业（省级）、高新技术企业认定等荣誉。", "legal_representative": "王雪颖", "general_manager": "王雪颖", "secretary": "周辉", "established_date": 1077033600000, "reg_asset": 326019466.0, "staff_num": 1045, "telephone": "86-28-61545795", "postcode": "611731", "fax": "86-28-87843532", "email": "ir@zhongguang.com;info@zhongguang.com", "org_website": "www.zhongguang.com", "reg_address_cn": "四川省成都市郫都区高新区西部园区天宇路19号", "reg_address_en": null, "office_address_cn": "四川省成都市郫都区高新区西部园区天宇路19号", "office_address_en": null, "currency_encode": "019001", "currency": "CNY", "listed_date": 1431446400000, "provincial_name": "四川省", "actual_controller": "王雪颖 (37.42%)", "classi_name": "民营企业", "pre_name_cn": null, "chairman": "王雪颖", "executives_nums": 10, "actual_issue_vol": 21070000.0, "issue_price": 14.74, "actual_rc_net_amt": 279206000.0, "pe_after_issuing": 13.24, "online_success_rate_of_issue": 0.29959852, "affiliate_industry": {"ind_code": "BK0029", "ind_name": "通信设备"}}}