{"company": {"org_id": "T004657364", "org_name_cn": "金三江(肇庆)硅材料股份有限公司", "org_short_name_cn": "金三江", "org_name_en": "Jinsanjiang(Zhaoqing)Silicon Material Company Limited", "org_short_name_en": "JSJ", "main_operation_business": "沉淀法二氧化硅的研发、生产和销售。", "operating_scope": "　　一般项目：基础化学原料制造（不含危险化学品等许可类化学品的制造）；货物或技术进出口（国家禁止或涉及行政审批的货物和技术进出口除外）。（除依法须经批准的项目外，凭营业执照依法自主开展经营活动）。", "district_encode": "441284", "org_cn_introduction": "金三江(肇庆)硅材料股份有限公司的主营业务是沉淀法二氧化硅的研发、生产和销售。公司的主要产品是牙膏用二氧化硅、食品、药品用二氧化硅、PE蓄电池隔板用二氧化硅、开口剂用二氧化硅。公司及子公司累计获得国家专利134项，其中中国发明专利104项、美国发明专利1项。", "legal_representative": "赵国法", "general_manager": "任振雪", "secretary": "任志霞", "established_date": 1070380800000, "reg_asset": 231154000.0, "staff_num": 374, "telephone": "86-758-3681267", "postcode": "526238", "fax": "86-758-3623858", "email": "ir@jsjgcl.com", "org_website": "www.gz-silica.com", "reg_address_cn": "广东省肇庆市四会市高新区迎宾大道23号(一照多址)", "reg_address_en": null, "office_address_cn": "广东省肇庆市四会市高新区创业路15号", "office_address_en": null, "currency_encode": "019001", "currency": "CNY", "listed_date": 1631462400000, "provincial_name": "广东省", "actual_controller": "任振雪 (40.35%)，赵国法 (28.93%)", "classi_name": "民营企业", "pre_name_cn": "肇庆金三江硅材料有限公司", "chairman": "赵国法", "executives_nums": 10, "actual_issue_vol": 30430000.0, "issue_price": 8.09, "actual_rc_net_amt": 204469500.0, "pe_after_issuing": 16.91, "online_success_rate_of_issue": 0.01512036, "affiliate_industry": {"ind_code": "BK0082", "ind_name": "美容护理"}}}