{"company": {"org_id": "02600816", "org_name_cn": "建元信托股份有限公司", "org_short_name_cn": "建元信托", "org_name_en": "J-Yuan Trust Co.,Ltd.", "org_short_name_en": "J-Yuan Trust", "main_operation_business": "固有业务、信托业务。", "operating_scope": "　　资金信托，动产信托，不动产信托，有价证券信托，其他财产或财产权信托，作为投资基金或者基金管理公司的发起人从事投资基金业务，经营企业资产的重组、购并及项目融资、公司理财、财务顾问等业务，受托经营国务院有关部门批准的证券承销业务，办理居间、咨询、资信调查等业务，代保管及保管箱业务，存放同业、拆放同业、贷款、租赁，投资方式运用固有财产，以固有财产为他人提供担保，从事同业拆借，法律法规规定或中国银行业监督管理委员会批准的其他业务，上述业务包括外汇业务。（依法须经批准的项目，经相关部门批准后方可开展经营活动）。", "district_encode": "310110", "org_cn_introduction": "建元信托股份有限公司的主营业务是固有业务、信托业务。公司的主要产品是固有业务、信托业务。", "legal_representative": "秦怿", "general_manager": "曾旭", "secretary": "王岗", "established_date": 811094400000, "reg_asset": 9844448254.0, "staff_num": 299, "telephone": "86-21-63410710", "postcode": "200001", "fax": "86-21-63410306", "email": "600816@j-yuantrust.com", "org_website": "www.j-yuantrust.com", "reg_address_cn": "上海市杨浦区控江路1553号-1555号A座301室", "reg_address_en": null, "office_address_cn": "上海市黄浦区广东路689号1/2/28/29楼", "office_address_en": null, "currency_encode": "019001", "currency": "CNY", "listed_date": 759686400000, "provincial_name": "上海市", "actual_controller": "高天国 (26.53%)", "classi_name": "民营企业", "pre_name_cn": "安信信托股份有限公司", "chairman": "秦怿", "executives_nums": 14, "actual_issue_vol": 49398000.0, "issue_price": 1.5, "actual_rc_net_amt": 74097000.0, "pe_after_issuing": null, "online_success_rate_of_issue": null, "affiliate_industry": {"ind_code": "BK0098", "ind_name": "多元金融"}}}