{"company": {"org_id": "T000668210", "org_name_cn": "西安中熔电气股份有限公司", "org_short_name_cn": "中熔电气", "org_name_en": "Xi'An Sinofuse Electric Co.,Ltd.", "org_short_name_en": "Sinofuse Electric", "main_operation_business": "熔断器及相关配件的研发、生产和销售。", "operating_scope": "　　电子和电气元器件、熔断器和开关及配件、电力和电气工具、电子和电气成套设备及配件、电子产品、汽车配件（不含汽车发动机）、机械设备（不含特种设备）及配件的研发、生产、销售；电力电子工程设计、施工（不含承装、承修、承试供电设施）；货物与技术的进出口经营（国家限制和禁止进出口的货物和技术除外）。（以上经营范围除国家规定的专控及许可项目）。", "district_encode": "610113", "org_cn_introduction": "西安中熔电气股份有限公司的主营业务是熔断器及相关配件的研发、生产和销售。公司的主要产品是电力熔断器及配件、电子类熔断器、激励熔断器。公司及子公司拥有有效专利共计279件，其中国内专利为266件，海外授权专利13件，其中发明专利33项，另有多项发明专利在申请过程中。公司还获得阳光电源“2024年创新突破奖”、比亚迪“2024年优秀供应商奖”、麦田能源“2024年最佳供应商奖”、先控捷联“2024年优秀供应商奖”、德业储能“2024年最佳创新奖”、协能科技“2024年优秀供应商奖”、徐州徐工“质量标兵荣誉”、英搏尔“2024年优秀合作伙伴奖”、威睿电动“2024年优秀质量奖”等多家客户的认可。", "legal_representative": "方广文", "general_manager": "方广文", "secretary": "刘冰", "established_date": 1176998400000, "reg_asset": 98322480.0, "staff_num": 1379, "telephone": "86-29-68590656", "postcode": "710000", "fax": "86-29-68590676", "email": "zjlbgs@sinofuse.com", "org_website": "www.sinofuse.com", "reg_address_cn": "陕西省西安市雁塔区高新区锦业二路97号中熔电气产业基地", "reg_address_en": null, "office_address_cn": "陕西省西安市雁塔区高新区锦业二路97号中熔电气产业基地", "office_address_en": null, "currency_encode": "019001", "currency": "CNY", "listed_date": 1626278400000, "provincial_name": "陕西省", "actual_controller": "方广文 (13.81%)，王伟 (3.62%)", "classi_name": "民营企业", "pre_name_cn": null, "chairman": "方广文", "executives_nums": 11, "actual_issue_vol": 16570000.0, "issue_price": 26.78, "actual_rc_net_amt": 396183657.0, "pe_after_issuing": 37.95, "online_success_rate_of_issue": 0.01118258, "affiliate_industry": {"ind_code": "BK0023", "ind_name": "其他电子"}}}