{"company": {"org_id": "00078490", "org_name_cn": "深圳康泰生物制品股份有限公司", "org_short_name_cn": "康泰生物", "org_name_en": "Shenzhen Kangtai Biological Products Co.,Ltd.", "org_short_name_en": "BioKangtai", "main_operation_business": "人用疫苗的研发、生产和销售。", "operating_scope": "　　开发、生产经营乙肝疫苗及其他医用生物制品；进出口业务（具体按资格证书办理）；投资兴办医药项目及其他实业（具体项目另行申报）；医药技术开发、信息咨询服务、自有房屋、设备租赁业务（不含限制项目）；普通货运；货物专用运输（冷藏保鲜）。", "district_encode": "440305", "org_cn_introduction": "深圳康泰生物制品股份有限公司的主营业务是人用疫苗的研发、生产和销售。公司的主要产品是13价肺炎球菌多糖结合疫苗、无细胞百白破b型流感嗜血杆菌联合疫苗（四联苗）、冻干人用狂犬病疫苗（人二倍体细胞）、23价肺炎球菌多糖疫苗、重组乙型肝炎疫苗(酿酒酵母)、b型流感嗜血杆菌结合疫苗、吸附无细胞百白破联合疫苗、水痘减毒活疫苗。", "legal_representative": "杜伟民", "general_manager": "苗向", "secretary": "陶瑾", "established_date": 715881600000, "reg_asset": 1116928663.0, "staff_num": 1913, "telephone": "86-755-26988558", "postcode": "518057", "fax": "86-755-26988600", "email": "office@biokangtai.com", "org_website": "www.biokangtai.com", "reg_address_cn": "广东省深圳市南山区粤海街道科技园社区科发路222号康泰集团大厦", "reg_address_en": null, "office_address_cn": "广东省深圳市南山区粤海街道科技园社区科发路222号康泰集团大厦", "office_address_en": null, "currency_encode": "019001", "currency": "CNY", "listed_date": 1486396800000, "provincial_name": "广东省", "actual_controller": "杜伟民 (25.50%)", "classi_name": "民营企业", "pre_name_cn": null, "chairman": "杜伟民", "executives_nums": 15, "actual_issue_vol": 42000000.0, "issue_price": 3.29, "actual_rc_net_amt": 111119500.0, "pe_after_issuing": 22.94, "online_success_rate_of_issue": 0.03828571, "affiliate_industry": {"ind_code": "BK0042", "ind_name": "生物制品"}}}