{"company": {"org_id": "T000072088", "org_name_cn": "天能电池集团股份有限公司", "org_short_name_cn": "天能股份", "org_name_en": "Tianneng Battery Group Co.,Ltd.", "org_short_name_en": "TN Battery", "main_operation_business": "电动轻型车动力电池业务、储能电池、特种车动力电池、汽车起动启停电池等多品类电池的研发、生产、销售。", "operating_scope": "　　高性能电池的研发、生产、销售；锂离子电池、燃料电池及其他储能环保电池、新型电极材料的研究开发、生产、销售；货物进出口和技术进出口（国家限定公司经营或禁止进出口的商品和技术除外）。（依法须经批准的项目，经相关部门批准后方可开展经营活动）", "district_encode": "330522", "org_cn_introduction": "天能电池集团股份有限公司的主营业务是电动轻型车动力电池业务、储能电池、特种车动力电池、汽车起动启停电池等多品类电池的研发、生产、销售。公司的主要产品是用于日常出行、物流快递、仓储搬运、环卫清洁、旅游观光等交通工具动力系统及起动启停系统，以及各类通信、电力、铁路、数码等储能电池及备用电源电池系统。其中，动力及储能电池为公司主要产品。公司共拥有专利3,536项，其中有14项专利荣获国家级、省级专利奖项，其中9项发明专利荣获中国专利优秀奖。", "legal_representative": "杨建芬", "general_manager": "杨建芬", "secretary": "胡敏翔", "established_date": 1047484800000, "reg_asset": 972100000.0, "staff_num": 19022, "telephone": "86-572-6029388", "postcode": "313100", "fax": "86-572-6129388", "email": "dshbgs@tianneng.com", "org_website": "www.cn-tn.com", "reg_address_cn": "浙江省湖州市长兴县煤山镇工业园区", "reg_address_en": null, "office_address_cn": "浙江省湖州市长兴县画溪工业园包桥路18号", "office_address_en": null, "currency_encode": "019001", "currency": "CNY", "listed_date": 1610899200000, "provincial_name": "浙江省", "actual_controller": "张天任 (31.18%)", "classi_name": "民营企业", "pre_name_cn": "天能电池集团有限公司", "chairman": "张天任", "executives_nums": 13, "actual_issue_vol": 116600000.0, "issue_price": 41.79, "actual_rc_net_amt": 4729733100.0, "pe_after_issuing": 30.98, "online_success_rate_of_issue": 0.03878992, "affiliate_industry": {"ind_code": "BK0096", "ind_name": "电池"}}}