{"company": {"org_id": "T000125664", "org_name_cn": "广东丸美生物技术股份有限公司", "org_short_name_cn": "丸美生物", "org_name_en": "Guangdong Marubi Biotechnology Co.,Ltd.", "org_short_name_en": "Marubi", "main_operation_business": "化妆品的研发、设计、生产、销售及服务。", "operating_scope": "　　化妆品制造；化妆品及卫生用品批发；化妆品及卫生用品零售；生物技术开发服务（我国稀有和特有的珍贵优良品种，国家保护的原产于我国的野生动、植物资源开发除外）；生物技术咨询、交流服务（我国稀有和特有的珍贵优良品种，国家保护的原产于我国的野生动、植物资源开发除外）；生物技术推广服务（我国稀有和特有的珍贵优良品种，国家保护的原产于我国的野生动、植物资源开发除外）；生物技术转让服务（我国稀有和特有的珍贵优良品种，国家保护的原产于我国的野生动、植物资源开发除外）；食品科学技术研究服务；货物进出口(涉及外资准入特别管理规定和许可审批的商品除外)；技术进出口；商品批发贸易（涉及外资准入特别管理规定和许可审批的商品除外）；商品零售贸易(涉及外资准入特别管理规定和许可审批的商品除外)；非许可类医疗器械经营；预包装食品批发；预包装食品零售。", "district_encode": "440112", "org_cn_introduction": "广东丸美生物技术股份有限公司的主营业务是化妆品的研发、设计、生产、销售及服务。公司的主要产品是眼部类、护肤类、洁肤类、美容及其他类。公司关键技术“重组胶原蛋白高效嵌合表达及抗衰研究”荣膺IFSCC“2025中国化妆品技术创新奖”。", "legal_representative": "孙怀庆", "general_manager": "孙怀庆", "secretary": "程迪", "established_date": 1017676800000, "reg_asset": 401000000.0, "staff_num": 1185, "telephone": "86-20-66378685", "postcode": "510000", "fax": "86-20-66378600", "email": "securities@marubi.cn", "org_website": "www.marubi.cn", "reg_address_cn": "广东省广州市黄埔区高新技术产业开发区科学城伴河路92号2号楼", "reg_address_en": null, "office_address_cn": "广东省广州市天河区珠江新城冼村路11号保利威座大厦南塔6楼", "office_address_en": null, "currency_encode": "019001", "currency": "CNY", "listed_date": 1563984000000, "provincial_name": "广东省", "actual_controller": "孙怀庆 (72.72%)，王晓蒲 (8.08%)", "classi_name": "外资企业", "pre_name_cn": "广州佳禾化妆品制造有限公司", "chairman": "孙怀庆", "executives_nums": 13, "actual_issue_vol": 41000000.0, "issue_price": 20.54, "actual_rc_net_amt": 790002000.0, "pe_after_issuing": 22.99, "online_success_rate_of_issue": 0.04164507, "affiliate_industry": {"ind_code": "BK0082", "ind_name": "美容护理"}}}