{"company": {"org_id": "T000184679", "org_name_cn": "广东日丰电缆股份有限公司", "org_short_name_cn": "日丰股份", "org_name_en": "Guangdong Rifeng Electric Cable Co.,Ltd.", "org_short_name_en": "RIFENG", "main_operation_business": "特种装备电缆、新能源电缆、通信装备以及其他电气设备电缆的研发、生产、销售。", "operating_scope": "　　许可项目：电线、电缆制造。(依法须经批准的项目,经相关部门批准后方可开展经营活动,具体经营项目以相关部门批准文件或许可证件为准)一般项目：电线、电缆经营;机械电气设备制造;机械电气设备销售;电子元器件与机电组件设备制造;电子元器件与机电组件设备销售;新型金属功能材料销售;有色金属压延加工;合成材料制造(不含危险化学品);合成材料销售;家用电器制造;家用电器销售;塑料制品制造;塑料制品销售;电器辅件销售;电器辅件制造;配电开关控制设备销售;配电开关控制设备制造;配电开关控制设备研发;五金产品批发;照明器具销售;照明器具制造;电子真空器件销售;家用电器零配件销售;非电力家用器具制造;非电力家用器具销售;电工器材制造;电工器材销售;智能家庭消费设备制造;智能家庭消费设备销售;橡胶制品销售;橡胶制品制造;输配电及控制设备制造;智能输配电及控制设备销售;技术服务、技术开发、技术咨询、技术交流、技术转让、技术推广;货物进出口;技术进出口。(除依法须经批准的项目外,凭营业执照依法自主开展经营活动)", "district_encode": "442000", "org_cn_introduction": "广东日丰电缆股份有限公司的主营业务是特种装备电缆、新能源电缆、通信装备以及其他电气设备电缆的研发、生产、销售。公司的主要产品是特种装备电缆、新能源电缆、通信装备组件、空调连接线组件、小家电配线组件。", "legal_representative": "冯就景", "general_manager": "李强", "secretary": "黎宇晖", "established_date": 1260979200000, "reg_asset": 456888849.0, "staff_num": 2839, "telephone": "86-760-85115672", "postcode": "528401", "fax": "86-760-85116269", "email": "rfgf@rfcable.com.cn", "org_website": "www.rfcable.com.cn", "reg_address_cn": "广东省中山市西区广丰工业园(一照多址)", "reg_address_en": null, "office_address_cn": "广东省中山市西区广丰工业园", "office_address_en": null, "currency_encode": "019001", "currency": "CNY", "listed_date": 1557331200000, "provincial_name": "广东省", "actual_controller": "冯就景 (51.61%)", "classi_name": "民营企业", "pre_name_cn": null, "chairman": "冯就景", "executives_nums": 10, "actual_issue_vol": 43020000.0, "issue_price": 10.52, "actual_rc_net_amt": 371200000.0, "pe_after_issuing": 16.34, "online_success_rate_of_issue": 0.02879319, "affiliate_industry": {"ind_code": "BK0093", "ind_name": "电网设备"}}}