{"company": {"org_id": "T000058465", "org_name_cn": "南京埃斯顿自动化股份有限公司", "org_short_name_cn": "埃斯顿", "org_name_en": "Estun Automation Co.,Ltd.", "org_short_name_en": "ESTUN AUTOMATION", "main_operation_business": "从自动化核心部件及运动控制系统、工业机器人、机器人工作站到智能制造系统的全产业链。", "operating_scope": "　　生产、开发、服务各类机电一体化产品、自动控制、运动控制、驱动装置、计算机应用软件、伺服液压控制及系统集成；销售自产产品。（依法须经批准的项目，经相关部门批准后方可开展经营活动）。", "district_encode": "320115", "org_cn_introduction": "南京埃斯顿自动化股份有限公司的主营业务是从自动化核心部件及运动控制系统、工业机器人、机器人工作站到智能制造系统的全产业链。公司的主要产品是自动化核心部件及运动控制系统、工业机器人及智能制造系统。公司为首批国家发展改革委、国家质检总局、工业和信息化部、国家认监委通过“中国机器人”认证的国产工业机器人企业，为工信部力推的“中国机器人TOP10”标杆企业之一。报告期内，公司光伏机器人获得工业和信息化部第八批“制造业单项冠军”，700kg重负载机器人（≥700kg负载）入选工业和信息化部印发《首台（套）重大技术装备推广应用指导目录（2024年版）》，机械安全2024年度《机械工业科学技术奖》二等奖，中国首张工业六轴关节机器人的cETLus证书以及莱茵TÜVCE机械指令及功能安全合规证书，InternetDeep机器人企业创新50强榜单第一、PVBL2024全球光伏品牌100强榜单、中国机电一体化技术应用协会第十届恰佩克年度机器人卓越品牌奖、工控网工业机器人年度创新产品奖、高工机器人2024年度创新产品（金球奖）、高工光伏新能源先锋奖、高工焊接机器人智能焊接产业链先进技术奖、传动网2024年度运动控制领域创新产品奖、2024年第五届中国工业机器人年会卓越销量奖。", "legal_representative": "吴波", "general_manager": "吴侃", "secretary": "肖婷婷", "established_date": 1014652800000, "reg_asset": 871018453.0, "staff_num": 3572, "telephone": "86-25-52785597", "postcode": "211106", "fax": "86-25-52785597", "email": "zqb@estun.com", "org_website": "www.estun.com", "reg_address_cn": "江苏省南京市江宁区吉印大道1888号(江宁开发区)", "reg_address_en": null, "office_address_cn": "江苏省南京市江宁区吉印大道1888号(江宁开发区)", "office_address_en": null, "currency_encode": "019001", "currency": "CNY", "listed_date": 1426780800000, "provincial_name": "江苏省", "actual_controller": "吴波 (41.29%)", "classi_name": "民营企业", "pre_name_cn": null, "chairman": "吴波", "executives_nums": 12, "actual_issue_vol": 30000000.0, "issue_price": 6.8, "actual_rc_net_amt": 170380000.0, "pe_after_issuing": 22.67, "online_success_rate_of_issue": 0.39131711, "affiliate_industry": {"ind_code": "BK0071", "ind_name": "自动化设备"}}}