{"company": {"org_id": "T000125850", "org_name_cn": "海波重型工程科技股份有限公司", "org_short_name_cn": "海波重科", "org_name_en": "Haibo Heavy Engineering Science And Technology Co.,Ltd.", "org_short_name_en": "Haibo", "main_operation_business": "桥梁钢结构的制作和安装,以及相应的技术研发、工艺设计及技术服务。", "operating_scope": "　　一般项目：金属结构制造；金属结构销售；建筑用金属配件制造；建筑用金属配件销售；金属表面处理及热处理加工；船用配套设备制造；喷涂加工；货物进出口；技术进出口；进出口代理；金属船舶制造；船舶销售；劳务服务（不含劳务派遣）；企业管理咨询；信息技术咨询服务；销售代理；国内贸易代理。（除许可业务外，可自主依法经营法律法规非禁止或限制的项目）许可项目：建设工程施工；施工专业作业；建筑劳务分包；船舶设计；船舶修理。（依法须经批准的项目，经相关部门批准后方可开展经营活动，具体经营项目以相关部门批准文件或许可证件为准）", "district_encode": "420115", "org_cn_introduction": "海波重型工程科技股份有限公司的主营业务是桥梁钢结构的制作和安装,以及相应的技术研发、工艺设计及技术服务。公司的主要产品是钢箱梁、钢桁架、钢箱拱桥结构、钢桁拱桥结构、钢管拱桥结构、悬索桥、斜拉桥、装配式钢混组合梁。", "legal_representative": "张海波", "general_manager": "答浩", "secretary": "张雪", "established_date": 860688000000, "reg_asset": 200409523.99999997, "staff_num": 164, "telephone": "86-27-87028626", "postcode": "430207", "fax": "86-27-87028378", "email": "hbzk_zqb@haiod.com", "org_website": "www.haiod.com", "reg_address_cn": "湖北省武汉市江夏区郑店街黄金桥工业园6号", "reg_address_en": null, "office_address_cn": "湖北省武汉市江夏区郑店街黄金桥工业园6号", "office_address_en": null, "currency_encode": "019001", "currency": "CNY", "listed_date": 1468857600000, "provincial_name": "湖北省", "actual_controller": "张海波 (49.33%)", "classi_name": "民营企业", "pre_name_cn": null, "chairman": "张海波", "executives_nums": 7, "actual_issue_vol": 25600000.0, "issue_price": 10.04, "actual_rc_net_amt": 227656400.0, "pe_after_issuing": 22.97, "online_success_rate_of_issue": 0.03713204, "affiliate_industry": {"ind_code": "BK0016", "ind_name": "建筑装饰"}}}