{"company": {"org_id": "T000061767", "org_name_cn": "深圳市索菱实业股份有限公司", "org_short_name_cn": "索菱股份", "org_name_en": "Shenzhen Soling Industrial Co.,Ltd.", "org_short_name_en": "soling", "main_operation_business": "汽车智能化及物联网通信。", "operating_scope": "　　一般经营项目是：汽车用收录(放)音机、车载CD、车载VCD、车载DVD(含GPS)液晶显示屏一体机、车载智能终端、汽车自动驾驶系统及软硬件、新能源汽车充电设施、新能源汽车动力电池、云计算软硬件、物联网智能设备的研发和销售；国内贸易（不含专营、专卖、专控商品）；经营进出口业务（法律、行政法规、国务院决定禁止的项目除外，限制的项目须取得许可后方可经营），与上述项目有关的技术开发、咨询；投资兴办实业。(以上均不含法律、行政法规、国务院决定禁止及规定需前置审批项目）。许可经营项目是：汽车用收录(放)音机、车载CD、车载VCD、车载DVD(含GPS)液晶显示屏一体机、车载智能终端、汽车自动驾驶系统及软硬件、新能源汽车充电设施、新能源汽车动力电池、云计算软硬件、物联网智能设备的生产。", "district_encode": "440305", "org_cn_introduction": "深圳市索菱实业股份有限公司的主营业务是汽车智能化及物联网通信。公司的主要产品是智能舱驾域控制器、商用车影音系统、播放器、中控、显示器、电子后视镜、商用车新国标终端、电子仪表、电动屏、商用车智能舱驾与5G终端。公司曾获“全国车联网企业100强”、“广东企业500强”、“广东制造业100强”等多项荣誉称号。", "legal_representative": "盛家方", "general_manager": "盛家方", "secretary": "蔡新辉", "established_date": 877017600000, "reg_asset": 861799823.9999999, "staff_num": 706, "telephone": "86-755-28022655", "postcode": "518000", "fax": "86-755-28022955", "email": "dm88@szsoling.com", "org_website": "www.szsoling.com", "reg_address_cn": "广东省深圳市南山区粤海街道海珠社区海德一道88号中洲控股金融中心B栋34M02", "reg_address_en": null, "office_address_cn": "广东省深圳市南山区粤海街道海珠社区海德一道88号中洲控股金融中心B栋3507", "office_address_en": null, "currency_encode": "019001", "currency": "CNY", "listed_date": 1433952000000, "provincial_name": "广东省", "actual_controller": "许培锋 (8.28%)", "classi_name": "民营企业", "pre_name_cn": null, "chairman": "盛家方", "executives_nums": 9, "actual_issue_vol": 45800000.0, "issue_price": 7.53, "actual_rc_net_amt": 313271000.0, "pe_after_issuing": 22.82, "online_success_rate_of_issue": 0.31532258, "affiliate_industry": {"ind_code": "BK0026", "ind_name": "汽车零部件"}}}