{"company": {"org_id": "T004399931", "org_name_cn": "襄阳长源东谷实业股份有限公司", "org_short_name_cn": "长源东谷", "org_name_en": "Xiangyang Changyuandonggu Industry Co.,Ltd.", "org_short_name_en": "CYDG", "main_operation_business": "柴油发动机零部件的研发、生产及销售。", "operating_scope": "　　机电设备（不含特种设备）安装；建筑工程施工（凭有效资质证书经营）；金属结构件、工位器具、汽车零部件（不含发动机）加工、销售；五金交电、五金工具、建材、通用设备及备件、仪器仪表、计量衡具的批零兼营；电线电缆（需办许可证的产品除外）生产储藏；普通货运；货物进出口（不含国家禁止或限制进出口的货物，不含分销）；有色金属、黑色金属材料的铸造及销售。（依法须经批准的项目，经相关部门批准后方可开展经营活动）", "district_encode": "420607", "org_cn_introduction": "襄阳长源东谷实业股份有限公司的主营业务是柴油发动机零部件的研发、生产及销售。公司的主要产品是柴油、天然气、汽油发动机缸体、缸盖、连杆、飞轮壳、主轴承盖、排气管及齿轮室、发动机零部件。公司被东风康明斯授予“风雨同舟20载卓越合作伙伴”、连续三年被广西康明斯授予优秀客户支持奖、连续三年被西安康明斯授予最佳支持奖、最佳交付奖、被广西玉柴授予2019年度国六最佳合作奖、2021年度战略协同奖、2023年度准时交付优秀奖、被上菲红授予2022年度优秀供应商、被东风商用车授予2021年度最佳供应商奖、2022年度COST活动优秀供应商、被上海新动力授予2022年度优秀合作奖、被弗迪动力授予2023年度优秀供应商。", "legal_representative": "李佐元", "general_manager": "李从容", "secretary": "刘网成", "established_date": 1008691200000, "reg_asset": 324130800.0, "staff_num": 2378, "telephone": "86-710-3062990", "postcode": "441104", "fax": "86-710-3062990", "email": "cydg2001@126.com", "org_website": "www.cydgsy.com", "reg_address_cn": "湖北省襄阳市襄州区钻石大道(洪山头工业园)", "reg_address_en": null, "office_address_cn": "湖北省襄阳市襄州区钻石大道(洪山头工业园)", "office_address_en": null, "currency_encode": "019001", "currency": "CNY", "listed_date": 1590422400000, "provincial_name": "湖北省", "actual_controller": "李佐元 (40.72%)，徐能琛 (11.22%)，李从容 (5.61%)，李险峰 (5.61%)", "classi_name": "外资企业", "pre_name_cn": "襄樊市长源东谷实业有限公司", "chairman": "李佐元", "executives_nums": 16, "actual_issue_vol": 57880500.0, "issue_price": 15.81, "actual_rc_net_amt": 883527030.0, "pe_after_issuing": 22.99, "online_success_rate_of_issue": 0.04038773, "affiliate_industry": {"ind_code": "BK0026", "ind_name": "汽车零部件"}}}