{"company": {"org_id": "03130715", "org_name_cn": "贵州钢绳股份有限公司", "org_short_name_cn": "贵绳股份", "org_name_en": "Guizhou Wire Rope Co.,Ltd.", "org_short_name_en": "GZWRC", "main_operation_business": "各种结构的钢绳产品、预应力钢绞线及相关设备、材料、技术的研究、生产、加工、销售及进出口业务；高科技产品的研制、开发与技术服务；索具加工、销售及进出口。", "operating_scope": "　　钢丝、钢绳产品及相关设备、材料、技术的研究、生产、加工、销售及进出口业务；相关科技产品的研制、开发与技术服务；混凝土用钢材(钢丝、钢棒和钢绞线)、线材、小型钢材、机器设备制造；建筑机电安装工程、索具加工、化工产品、铁路普通货物运输等。", "district_encode": "520302", "org_cn_introduction": "贵州钢绳股份有限公司的主营业务是各种结构的钢绳产品、预应力钢绞线及相关设备、材料、技术的研究、生产、加工、销售及进出口业务；高科技产品的研制、开发与技术服务；索具加工、销售及进出口。公司的主要产品是钢丝、钢丝绳、钢绞线。公司“巨龙”牌钢丝绳多次在中国质量管理协会组织的用户调查中被评为“用户满意产品”，公司“巨龙”牌钢丝绳连续被评为“中国名牌产品”，被认定为中国免检产品，形成了较高的品牌效应。公司继获得“全国制造业单项冠军示范企业”“全国工业品牌培育示范企业”“国家技术创新示范企业”“中国质量奖提名奖”“中国工业大奖提名奖”“ISO2408：2017技术标准优秀奖壹等奖”“全国冶金行业质量领先企业”“全国质量信用优秀企业”“全国百佳质量检验诚信标杆企业”“全国产品和服务质量诚信示范企业”“全国质量检验稳定合格产品”“2020年度贵州省科技进步一等奖”“2021年度中国钢铁工业协会中国金属学会冶金科学技术三等奖”“2022年度中国钢结构协会技术创新奖”“2022年度贵州省科技厅十大科技创新成果奖”“2023年度中建集团科学技术奖一等奖”等荣誉后，报告期内，制造业单项冠军企业复核通过并于2024年4月颁发证书而继续保持其称号，在花江峡谷大桥主缆产品实现了智慧赋能集成应用。", "legal_representative": "马显红", "general_manager": "杨程", "secretary": "曹磊", "established_date": 971884800000, "reg_asset": 245090000.0, "staff_num": 3442, "telephone": "86-851-28419570", "postcode": "563000", "fax": "86-851-28419570", "email": "zqb@gzgs.com.cn;office@gzgs.com.cn", "org_website": "www.gzgsgf.com.cn", "reg_address_cn": "贵州省遵义市红花岗区桃溪路47号", "reg_address_en": null, "office_address_cn": "贵州省遵义市红花岗区桃溪路47号", "office_address_en": null, "currency_encode": "019001", "currency": "CNY", "listed_date": 1084464000000, "provincial_name": "贵州省", "actual_controller": "贵州省人民政府国有资产监督管理委员会 (15.36%)", "classi_name": "省属国资控股", "pre_name_cn": null, "chairman": "马显红", "executives_nums": 18, "actual_issue_vol": 70000000.0, "issue_price": 7.4, "actual_rc_net_amt": 496870000.0, "pe_after_issuing": 16.8, "online_success_rate_of_issue": null, "affiliate_industry": {"ind_code": "BK0017", "ind_name": "通用设备"}}}