{"company": {"org_id": "03130171", "org_name_cn": "时代出版传媒股份有限公司", "org_short_name_cn": "时代出版", "org_name_en": "Time Publishing & Media Co.,Ltd.", "org_short_name_en": "Time Publishing & Media Co.,Ltd.", "main_operation_business": "图书期刊出版、新媒体出版、素质教育课后服务、印刷复制、文化产品贸易、股权投资。", "operating_scope": "　　资产管理、运营、投资以及对所属全资及控股子公司资产或股权进行管理，融资咨询服务；对所属企业国（境）内外图书、期刊、报纸、电子出版物、音像制品、网络出版物的出版、销售、物流配送、连锁经营进行管理；版权代理；图书加工；展示展览服务；文化用品的批发和零售；出版印刷物资贸易；教育培训咨询服务；广告业务；出版咨询服务；图书总发行；新兴传媒科研、开发、推广和应用；电子和信息、光电机一体化、化工（不含危险品）、新材料、生物工程、环保、节能、医疗器械（限中佳分公司经营）、核仪器、电工电器、机械真空、离子束、微波通讯、自动控制、辐射加工、KG型纺织印染助剂、环保型建筑涂料开发、生产、销售及咨询服务、技术转让；涂料装饰工程施工；房屋租赁。（以上须经批准的项目，经相关部门批准后方可开展经营活动）", "district_encode": "340104", "org_cn_introduction": "时代出版传媒股份有限公司的主营业务是图书期刊出版、新媒体出版、素质教育课后服务、印刷复制、文化产品贸易、股权投资。公司的主要产品是教材的代理发行、一般图书、期刊、电子出版物、音像制品、数字出版物、教辅编辑出版、在线教育、数字出版、其它新媒体业务拓展、教育服务业务、印刷包装业务、纸张、印刷设备及相关文化产品的采购贸易、购买理财产品、委托贷款、股权投资、自营商业地产运营、影视投资。公司先后荣获中国出版政府奖先进出版单位奖、“走出去”先进集体奖、中国版权金奖、中国图书对外推广计划特别贡献奖、世界媒体500强、中国上市公司综合实力100强、中国上市公司最具投资价值100强，荣膺首批现代服务业创新发展示范企业、中国版权产业最具影响力企业、国家文化出口重点企业、首批国家数字出版转型示范单位等诸多荣誉，入选2023年度“全国文化企业30强”，社会效益日益彰显，两个效益更加优化，主业竞争力稳步提升。", "legal_representative": "董磊", "general_manager": "郑可", "secretary": "李仕兵", "established_date": 944928000000, "reg_asset": 678055239.0, "staff_num": 1870, "telephone": "86-551-63533050;86-551-63533053", "postcode": "230071", "fax": "86-551-63533185", "email": "gongsixinxiang@press-mart.com;zhengquan@press-mart.com;luyl@press-mart.com", "org_website": "www.press-mart.com", "reg_address_cn": "安徽省合肥市蜀山区长江西路669号", "reg_address_en": null, "office_address_cn": "安徽省合肥市蜀山区翡翠路1118号出版传媒广场", "office_address_en": null, "currency_encode": "019001", "currency": "CNY", "listed_date": 1031155200000, "provincial_name": "安徽省", "actual_controller": "安徽省人民政府 (62.09%)", "classi_name": "省属国资控股", "pre_name_cn": "科大创新股份有限公司", "chairman": "董磊", "executives_nums": 12, "actual_issue_vol": 25000000.0, "issue_price": 4.0, "actual_rc_net_amt": 93280000.0, "pe_after_issuing": 20.0, "online_success_rate_of_issue": null, "affiliate_industry": {"ind_code": "BK0064", "ind_name": "文化传媒"}}}