{"company": {"org_id": "Q0000C155A", "org_name_cn": "王力安防科技股份有限公司", "org_short_name_cn": "王力安防", "org_name_en": "Wangli Security & Surveillance Product Co.,Ltd.", "org_short_name_en": "WONLY", "main_operation_business": "安全门等门类产品以及机械锁和智能锁等锁具产品的研发、设计、生产、销售和服务。", "operating_scope": "　　一般项目：金属制品研发；金属制品销售；门窗制造加工；门窗销售；五金产品研发；五金产品制造；五金产品零售；涂料制造（不含危险化学品）；涂料销售（不含危险化学品）；智能家庭消费设备制造；智能家庭消费设备销售；网络设备销售；通讯设备销售；机械电气设备销售；仪器仪表销售；第二类医疗器械销售；物联网技术研发；物联网技术服务；物联网设备制造；物联网设备销售；工业自动控制系统装置销售；智能基础制造装备销售；智能物料搬运装备销售；智能仓储装备销售；人工智能基础软件开发；人工智能应用软件开发；信息系统集成服务；信息技术咨询服务；信息系统运行维护服务；计算机软硬件及辅助设备批发；计算机软硬件及辅助设备零售；技术服务、技术开发、技术咨询、技术交流、技术转让、技术推广；货物进出口；技术进出口；金属门窗工程施工（除依法须经批准的项目外，凭营业执照依法自主开展经营活动）。许可项目：住宅室内装饰装修；第二类增值电信业务；建筑智能化系统设计（依法须经批准的项目，经相关部门批准后方可开展经营活动，具体经营项目以审批结果为准）。", "district_encode": "330784", "org_cn_introduction": "王力安防科技股份有限公司的主营业务是安全门等门类产品以及机械锁和智能锁等锁具产品的研发、设计、生产、销售和服务。公司的主要产品是钢质安全门、其他门、智能锁。公司先后通过ISO9001质量管理体系认证、ISO14001环境管理体系认证、ISO45001职业健康安全管理体系认证，并取得了《两化融合管理体系评定证书》《浙江制造认证证书》《绿色建材产品认证证书》《防火门产品认证证书》和《GA产品认证证书》等一系列证书，荣获了德国红点至尊奖、IF设计大奖、高新技术企业、智能锁质量安全奖、公安部科学技术奖等诸多荣誉。", "legal_representative": "王跃斌", "general_manager": "王跃斌", "secretary": "陈泽鹏", "established_date": 1112025600000, "reg_asset": 446302500.0, "staff_num": 4391, "telephone": "86-579-89297839", "postcode": "321300", "fax": "86-579-87228555", "email": "wanglianfangdongsb@163.com", "org_website": "www.wanglianfang.com", "reg_address_cn": "浙江省金华市永康市经济开发区爱岗路9号", "reg_address_en": null, "office_address_cn": "浙江省金华市永康市经济开发区爱岗路9号", "office_address_en": null, "currency_encode": "019001", "currency": "CNY", "listed_date": 1614096000000, "provincial_name": "浙江省", "actual_controller": "王跃斌 (33.68%)，陈晓君 (26.64%)，王琛 (15.24%)", "classi_name": "民营企业", "pre_name_cn": null, "chairman": "王跃斌", "executives_nums": 13, "actual_issue_vol": 67000000.0, "issue_price": 10.32, "actual_rc_net_amt": 598506500.0, "pe_after_issuing": 22.97, "online_success_rate_of_issue": 0.04381771, "affiliate_industry": {"ind_code": "BK0039", "ind_name": "家居用品"}}}