{"company": {"org_id": "T000251838", "org_name_cn": "苏州骏创汽车科技股份有限公司", "org_short_name_cn": "骏创科技", "org_name_en": "Suzhou Junchuang Auto Technologies Co.,Ltd.", "org_short_name_en": null, "main_operation_business": "研发、生产、销售汽车塑料零部件、汽车金属零件以及相关配套模具的开发。", "operating_scope": "　　许可项目：技术进出口；货物进出口（依法须经批准的项目，经相关部门批准后方可开展经营活动，具体经营项目以审批结果为准）；一般项目：汽车零部件研发；汽车零部件及配件制造；汽车零配件零售；第一类医疗器械生产；第一类医疗器械销售；塑料制品制造；塑料制品销售；模具制造；模具销售；信息技术咨询服务；非居住房地产租赁；机械设备租赁；办公设备租赁服务；机械设备销售；工业机器人安装、维修；工业机器人制造；工业机器人销售；塑料加工专用设备制造；塑料加工专用设备销售（除依法须经批准的项目外，凭营业执照依法自主开展经营活动）", "district_encode": "320506", "org_cn_introduction": "苏州骏创汽车科技股份有限公司的主营业务是研发、生产、销售汽车塑料零部件、汽车金属零件以及相关配套模具的开发。公司的主要产品是汽车塑料零部件、配套模具。公司于2022年10月12日获得江苏省科学技术厅、江苏省财政厅、江苏省国家税务局共同颁发的高新技术企业证书（证书编号GR202232003690，有效期3年）。", "legal_representative": "沈安居", "general_manager": "沈安居", "secretary": "陈显鲁", "established_date": 1119456000000, "reg_asset": 130757328.0, "staff_num": 793, "telephone": "86-512-65022868", "postcode": "215101", "fax": "86-512-66570981", "email": "tangmanhong@szjunchuang.com", "org_website": "www.szjunchuang.com", "reg_address_cn": "江苏省苏州市吴中区木渎镇船坊头路6号", "reg_address_en": null, "office_address_cn": "江苏省苏州市吴中区木渎镇船坊头路6号", "office_address_en": null, "currency_encode": "019001", "currency": "CNY", "listed_date": 1653321600000, "provincial_name": "江苏省", "actual_controller": "沈安居 (54.99%)，李祥平 (3.56%)", "classi_name": "民营企业", "pre_name_cn": null, "chairman": "沈安居", "executives_nums": 9, "actual_issue_vol": 8600000.0, "issue_price": 12.5, "actual_rc_net_amt": 93291642.0, "pe_after_issuing": 24.87, "online_success_rate_of_issue": 0.48, "affiliate_industry": {"ind_code": "BK0026", "ind_name": "汽车零部件"}}}