{"company": {"org_id": "T000032760", "org_name_cn": "天山铝业集团股份有限公司", "org_short_name_cn": "天山铝业", "org_name_en": "Tianshan Aluminum Group Co.,Ltd.", "org_short_name_en": "TIANSHAN ALUMINUM", "main_operation_business": "电解铝、氧化铝、预焙阳极、高纯铝、铝深加工产品及材料的生产和销售。", "operating_scope": "　　许可项目：进出口代理；货物进出口；矿产资源（非煤矿山）开采；技术进出口（依法须经批准的项目，经相关部门批准后方可开展经营活动，具体经营项目以审批结果为准）。一般项目：石墨及碳素制品销售；石墨及碳素制品制造；金属材料销售；金属材料制造；常用有色金属冶炼；有色金属压延加工；装卸搬运；普通货物仓储服务（不含危险化学品等需许可审批的项目）；矿物洗选加工；选矿；建筑砌块制造；建筑砌块销售（除依法须经批准的项目外，凭营业执照依法自主开展经营活动）。", "district_encode": "331081", "org_cn_introduction": "天山铝业集团股份有限公司的主营业务是电解铝、氧化铝、预焙阳极、高纯铝、铝深加工产品及材料的生产和销售。公司的主要产品是自产铝锭、高纯铝、外购铝锭、自产铝制品、氧化铝、铝箔、铝箔坯料。2021年1月，天山铝业获批成为第一批符合新版《铝行业规范条件》的铝业企业，是目前国内具有合规产能单厂规模第二大的公司。2022年8月，新疆天展新材料科技有限公司成功入选工信部第四批国家级专精特新“小巨人”企业名单。2023年2月，天铝有限入选国家工信部2022年度绿色工厂名单。2024年7月，天山铝业再次入选《财富》中国500强榜单，位列第468名。2024年9月，天铝有限再次荣登《中国民营企业500强榜单》，位列第470位，同时连续九年荣登《中国制造业民营企业500强榜单》，位列第312位。2024年10月，天铝有限《大型预焙电解槽节能降耗关键技术及工程应用》荣获新疆生产建设兵团科学技术进步二等奖。2024年11月，天铝有限入选兵团工业企业100强榜单，位列第1forgettable17名；同时，南疆碳素也入选该榜单，位列第80名。2024年11月，靖西天桂入选广西民营企业100强榜单。", "legal_representative": "曾超林", "general_manager": "曾超林", "secretary": "周建良", "established_date": 878486400000, "reg_asset": 4651885415.0, "staff_num": 6756, "telephone": "86-21-58773690", "postcode": "200135", "fax": "86-21-68862900", "email": "002532@tslyjt.com", "org_website": "www.tslyjt.com", "reg_address_cn": "浙江省台州市温岭市大溪镇大洋城工业区", "reg_address_en": null, "office_address_cn": "上海市浦东新区张杨路2389弄3号普洛斯大厦9层", "office_address_en": null, "currency_encode": "019001", "currency": "CNY", "listed_date": 1293724800000, "provincial_name": "浙江省", "actual_controller": "曾超懿 (21.98%)，曾超林 (20.01%)", "classi_name": "民营企业", "pre_name_cn": "新界泵业集团股份有限公司", "chairman": "曾超林", "executives_nums": 11, "actual_issue_vol": 20000000.0, "issue_price": 32.88, "actual_rc_net_amt": 611873600.0, "pe_after_issuing": 58.71, "online_success_rate_of_issue": 0.68513021, "affiliate_industry": {"ind_code": "BK0068", "ind_name": "工业金属"}}}